<?xml version="1.0" encoding="utf-8" ?>
<dwsync>
<file name="joiner.php" server="172.17.1.26//var/www/html/" local="130477456050000000" remote="130477456050000000" />
<file name="init.js" server="172.17.1.26//var/www/html/" local="130477456050000000" remote="130477456050000000" />
<file name="toolbar.js" server="172.17.1.26//var/www/html/" local="130477456050000000" remote="130477456050000000" />
<file name="settings.js" server="172.17.1.26//var/www/html/" local="130477456050000000" remote="130477456050000000" />
<file name="0bject.js" server="172.17.1.26//var/www/html/" local="130477456050000000" remote="130477456050000000" />
<file name="misc.js" server="172.17.1.26//var/www/html/" local="130477456050000000" remote="130477456050000000" />
<file name="files.js" server="172.17.1.26//var/www/html/" local="130477456050000000" remote="130477456050000000" />
<file name="folders.js" server="172.17.1.26//var/www/html/" local="130477456050000000" remote="130477456050000000" />
<file name="clipboard.js" server="172.17.1.26//var/www/html/" local="130477456050000000" remote="130477456050000000" />
</dwsync>