<?xml version="1.0" encoding="utf-8" ?>
<dwsync>
<file name="bt_close.png" server="172.17.1.26//var/www/html/" local="130477456050000000" remote="130477456050000000" />
<file name="tab_b.png" server="172.17.1.26//var/www/html/" local="130477456050000000" remote="130477456050000000" />
<file name="tab_m.png" server="172.17.1.26//var/www/html/" local="130477456050000000" remote="130477456050000000" />
<file name="Thumbs.db" server="172.17.1.26//var/www/html/" local="130477456050000000" remote="130477456050000000" />
<file name="bt_open.png" server="172.17.1.26//var/www/html/" local="130477456050000000" remote="130477456050000000" />
<file name="bt_register.png" server="172.17.1.26//var/www/html/" local="130477456050000000" remote="130477456050000000" />
<file name="bg.jpg" server="172.17.1.26//var/www/html/" local="130477456050000000" remote="130477456050000000" />
<file name="bt_login.png" server="172.17.1.26//var/www/html/" local="130477456050000000" remote="130477456050000000" />
<file name="tab_r.png" server="172.17.1.26//var/www/html/" local="130477456050000000" remote="130477456050000000" />
<file name="tab_l.png" server="172.17.1.26//var/www/html/" local="130477456050000000" remote="130477456050000000" />
</dwsync>